snnmetrics/__init__.py
snnmetrics/synops.py
snnmetrics-0.0.1.dist-info/AUTHORS
snnmetrics-0.0.1.dist-info/METADATA
snnmetrics-0.0.1.dist-info/WHEEL
snnmetrics-0.0.1.dist-info/pbr.json
snnmetrics-0.0.1.dist-info/top_level.txt
snnmetrics-0.0.1.dist-info/RECORD
