Metadata-Version: 2.1
Name: snnmetrics
Version: 0.0.1
Summary: Metrics for spiking neural networks.
Author: Gregor Lenz
Author-email: mail@lenzgregor.com
License: GNU GPLv3
Project-URL: Source code, https://github.com
Project-URL: Documentation, https://snnmetrics.readthedocs.org
Classifier: Intended Audience :: Science/Research
Classifier: License :: OSI Approved :: GNU General Public License v3 (GPLv3)
Classifier: Programming Language :: Python :: 3
Classifier: Operating System :: OS Independent
License-File: AUTHORS
Requires-Dist: torchmetrics
